README.md
setup.py
distributed_counter/__init__.py
distributed_counter/distributed_counter.py
distributed_counter.egg-info/PKG-INFO
distributed_counter.egg-info/SOURCES.txt
distributed_counter.egg-info/dependency_links.txt
distributed_counter.egg-info/requires.txt
distributed_counter.egg-info/top_level.txt
test/test_atomicity.py
test/test_basic.py