Metadata-Version: 2.1
Name: distributed_counter
Version: 0.0.3
Summary: distributed increment/decrement counter leveraging dynamodb
Home-page: https://github.com/wontonst/distributed-counter-py
Author: Roy Zheng
License: UNKNOWN
Platform: UNKNOWN
